README.md
setup.py
pygame_toolkit/__init__.py
pygame_toolkit/core.py
pygame_toolkit.egg-info/PKG-INFO
pygame_toolkit.egg-info/SOURCES.txt
pygame_toolkit.egg-info/dependency_links.txt
pygame_toolkit.egg-info/requires.txt
pygame_toolkit.egg-info/top_level.txt
pygame_toolkit/tools/__init__.py
pygame_toolkit/tools/font_finder.py
pygame_toolkit/tools/font_loader.py
pygame_toolkit/uix/__init__.py
pygame_toolkit/uix/button.py
pygame_toolkit/uix/container.py
pygame_toolkit/uix/multiline_text.py
pygame_toolkit/uix/polygonal_graph.py
pygame_toolkit/uix/text.py