Metadata-Version: 2.1
Name: pygame-toolkit
Version: 0.3
Summary: Tools for use with pygame
Home-page: UNKNOWN
Author: Vinicius Putti Morais
Author-email: viniputtim@gmail.com
License: UNKNOWN
Platform: UNKNOWN
